von/__init__.py
von/test.py
von-0.1a0.dist-info/LICENSE
von-0.1a0.dist-info/METADATA
von-0.1a0.dist-info/WHEEL
von-0.1a0.dist-info/entry_points.txt
von-0.1a0.dist-info/top_level.txt
von-0.1a0.dist-info/RECORD
