Metadata-Version: 2.1
Name: von
Version: 0.1a0
Summary: test pip package
Home-page: https://github.com/nagendra-2k3/von
Author: Nagendra_2k3
Author-email: <vozon.537@gmail.com>
License: MIT
Platform: UNKNOWN
